mssql_mcp_server/__init__.py
mssql_mcp_server/__main__.py
mssql_mcp_server/server.py
pyodbc_mcp_server-0.2.2.dist-info/METADATA
pyodbc_mcp_server-0.2.2.dist-info/WHEEL
pyodbc_mcp_server-0.2.2.dist-info/entry_points.txt
pyodbc_mcp_server-0.2.2.dist-info/licenses/LICENSE
pyodbc_mcp_server-0.2.2.dist-info/RECORD
