Metadata-Version: 2.4
Name: pyodbc-mcp-server
Version: 0.2.2
Summary: MCP server for read-only SQL Server access via Windows Authentication
Project-URL: Homepage, https://github.com/jjones-wps/pyodbc-mcp-server
Project-URL: Repository, https://github.com/jjones-wps/pyodbc-mcp-server
Project-URL: Issues, https://github.com/jjones-wps/pyodbc-mcp-server/issues
Author: Jack Jones
License-Expression: MIT
License-File: LICENSE
Keywords: ai,claude,claude-code,database,mcp,model-context-protocol,mssql,sql-server,windows-authentication
Classifier: Development Status :: 4 - Beta
Classifier: Intended Audience :: Developers
Classifier: License :: OSI Approved :: MIT License
Classifier: Operating System :: Microsoft :: Windows
Classifier: Programming Language :: Python :: 3
Classifier: Programming Language :: Python :: 3.10
Classifier: Programming Language :: Python :: 3.11
Classifier: Programming Language :: Python :: 3.12
Classifier: Topic :: Database
Classifier: Topic :: Software Development :: Libraries :: Python Modules
Requires-Python: >=3.10
Requires-Dist: anyio>=4.0.0
Requires-Dist: fastmcp>=2.0.0
Requires-Dist: pyodbc>=5.0.0
Provides-Extra: dev
Requires-Dist: mypy>=1.0.0; extra == 'dev'
Requires-Dist: pre-commit>=3.5.0; extra == 'dev'
Requires-Dist: pytest-asyncio>=0.23.0; extra == 'dev'
Requires-Dist: pytest-cov>=4.0.0; extra == 'dev'
Requires-Dist: pytest>=7.0.0; extra == 'dev'
Requires-Dist: ruff>=0.8.0; extra == 'dev'
